pureskillgg_csgo_dsdk/__init__.py
pureskillgg_csgo_dsdk/errors/__init__.py
pureskillgg_csgo_dsdk/errors/channel_structure.py
pureskillgg_csgo_dsdk/overtime/__init__.py
pureskillgg_csgo_dsdk/overtime/pop_overtime.py
pureskillgg_csgo_dsdk/overtime/pop_overtime_test.py
pureskillgg_csgo_dsdk/scrubber/__init__.py
pureskillgg_csgo_dsdk/scrubber/scrub_pii.py
pureskillgg_csgo_dsdk/scrubber/scrub_pii_test.py
pureskillgg_csgo_dsdk-2.0.0.dist-info/LICENSE.txt
pureskillgg_csgo_dsdk-2.0.0.dist-info/WHEEL
pureskillgg_csgo_dsdk-2.0.0.dist-info/METADATA
pureskillgg_csgo_dsdk-2.0.0.dist-info/RECORD
