Metadata-Version: 2.1
Name: pureskillgg-csgo-dsdk
Version: 2.0.0
Summary: Python Data Science Development Kit for CS:GO.
Home-page: https://github.com/pureskillgg/csgo-dsdk
License: MIT
Author: PureSkill.gg
Author-email: contact@pureskill.gg
Requires-Python: >=3.9,<4.0
Classifier: License :: OSI Approved :: MIT License
Classifier: Programming Language :: Python :: 3
Classifier: Programming Language :: Python :: 3.9
Classifier: Programming Language :: Python :: 3.10
Requires-Dist: pandas[aws,computation,fss,output-formatting,parquet,performance,plot] (>=2.2.1,<3.0.0)
Requires-Dist: pureskillgg-dsdk (>=2.0.0,<3.0.0)
Requires-Dist: structlog (>=22.1.0,<23.0.0)
Project-URL: Repository, https://github.com/pureskillgg/csgo-dsdk
